grafiti/__init__.py
grafiti/grafiti.py
grafiti/runner.py
grafiti-0.1.1.dist-info/WHEEL
grafiti-0.1.1.dist-info/METADATA
grafiti-0.1.1.dist-info/RECORD
